app_store_review_etl/__init__.py
app_store_review_etl/logger.py
app_store_review_etl/main.py
app_store_review_etl/settings.py
app_store_review_etl/utils.py
app_store_review_etl/google_sheets_auth/__init__.py
app_store_review_etl/google_sheets_auth/google_sheets_auth.py
app_store_review_etl/pipeline/__init__.py
app_store_review_etl/pipeline/pipeline.py
app_store_review_etl/pipeline/steps/__init__.py
app_store_review_etl/pipeline/steps/fetch_app_reviews.py
app_store_review_etl/pipeline/steps/graph.py
app_store_review_etl/pipeline/steps/postflight.py
app_store_review_etl/pipeline/steps/preflight.py
app_store_review_etl/pipeline/steps/sentiment_analysis.py
app_store_review_etl/pipeline/steps/step.py
app_store_review_etl/pipeline/steps/top_liked_disliked_analysis.py
app_store_review_etl/pipeline/steps/update_graph.py
app_store_review_etl/pipeline/steps/word_cloud_graph.py
app_store_review_etl-0.1.0.dist-info/LICENSE
app_store_review_etl-0.1.0.dist-info/METADATA
app_store_review_etl-0.1.0.dist-info/WHEEL
app_store_review_etl-0.1.0.dist-info/top_level.txt
app_store_review_etl-0.1.0.dist-info/RECORD
