Metadata-Version: 2.1
Name: app-store-review-etl
Version: 0.1.0
Summary: AI-powered app store reviews analysis tool
Home-page: https://github.com/whygreedy/app-store-review-etl
Author: Cindy Yeh
Author-email: cindyyeah9@gmail.com
License: MIT
Classifier: License :: OSI Approved :: MIT License
Classifier: Programming Language :: Python
Classifier: Programming Language :: Python :: 3
Classifier: Programming Language :: Python :: 3.6
Classifier: Programming Language :: Python :: Implementation :: CPython
Classifier: Programming Language :: Python :: Implementation :: PyPy
Requires-Python: >=3.9.0
License-File: LICENSE
Requires-Dist: app-store-scraper
Requires-Dist: gspread
Requires-Dist: vaderSentiment
Requires-Dist: google-generativeai
Requires-Dist: wordcloud
Requires-Dist: matplotlib
Requires-Dist: python-dotenv
